langchain_scraperapi/__init__.py
langchain_scraperapi/py.typed
langchain_scraperapi/tools.py
langchain_scraperapi/utils.py
langchain_scraperapi-0.1.1.dist-info/LICENSE
langchain_scraperapi-0.1.1.dist-info/METADATA
langchain_scraperapi-0.1.1.dist-info/WHEEL
langchain_scraperapi-0.1.1.dist-info/RECORD
