Metadata-Version: 2.3
Name: langchain-scraperapi
Version: 0.1.1
Summary: An integration package connecting ScraperAPI and LangChain
License: MIT
Author: scraperapi
Requires-Python: >=3.9,<4.0
Classifier: License :: OSI Approved :: MIT License
Classifier: Programming Language :: Python :: 3
Classifier: Programming Language :: Python :: 3.9
Classifier: Programming Language :: Python :: 3.10
Classifier: Programming Language :: Python :: 3.11
Classifier: Programming Language :: Python :: 3.12
Classifier: Programming Language :: Python :: 3.13
Requires-Dist: aiohttp (>=3.11.16,<4.0.0)
Requires-Dist: langchain (>=0.3.20,<0.4.0)
Requires-Dist: langchain-core (>=0.3.15,<0.4.0)
Requires-Dist: scraperapi-sdk (>=1.5.3,<2.0.0)
Project-URL: Repository, https://github.com/scraperapi/langchain-scraperapi
Project-URL: Source Code, https://github.com/langchain-ai/langchain/tree/master/libs/partners/scraperapi
